odoo/addons/project_list/README.rst
odoo/addons/project_list/__init__.py
odoo/addons/project_list/__manifest__.py
odoo/addons/project_list/i18n/de.po
odoo/addons/project_list/i18n/hr.po
odoo/addons/project_list/i18n/it.po
odoo/addons/project_list/i18n/project_list.pot
odoo/addons/project_list/i18n/pt_BR.po
odoo/addons/project_list/i18n/sl.po
odoo/addons/project_list/readme/CONTRIBUTORS.rst
odoo/addons/project_list/readme/DESCRIPTION.rst
odoo/addons/project_list/static/description/icon.png
odoo/addons/project_list/static/description/index.html
odoo/addons/project_list/views/project_project.xml
odoo12_addon_project_list-12.0.1.0.0.99.dev11.dist-info/METADATA
odoo12_addon_project_list-12.0.1.0.0.99.dev11.dist-info/WHEEL
odoo12_addon_project_list-12.0.1.0.0.99.dev11.dist-info/top_level.txt
odoo12_addon_project_list-12.0.1.0.0.99.dev11.dist-info/RECORD
